synapsex_sdk/__init__.py
synapsex_sdk/synapsex_sdk.cpython-311-x86_64-linux-gnu.so
synapsex-1.0.9.dist-info/METADATA
synapsex-1.0.9.dist-info/WHEEL
synapsex-1.0.9.dist-info/top_level.txt
synapsex-1.0.9.dist-info/RECORD
