Metadata-Version: 2.4
Name: synapsex
Version: 1.0.9
Summary: SynapseX SDK - Enterprise AI
Requires-Python: >=3.9
Requires-Dist: requests>=2.31.0
Requires-Dist: pydantic>=2.0.0
